README.md
setup.py
excel_picture/__init__.py
excel_picture/excel_picture.py
excel_picture.egg-info/PKG-INFO
excel_picture.egg-info/SOURCES.txt
excel_picture.egg-info/dependency_links.txt
excel_picture.egg-info/entry_points.txt
excel_picture.egg-info/requires.txt
excel_picture.egg-info/top_level.txt