Metadata-Version: 2.1
Name: excel-picture
Version: 0.2.0
Summary: This is a tool that can quickly locate the path of the picture, it is very easy to use
Home-page: https://github.com/xizhicode/excel_picture.git
Author: zhaohengping
Author-email: 13073771301@163.com
Maintainer: zhaohengping
Maintainer-email: zhaohengping@gongchang.com
License: GPL-2.0
Platform: UNKNOWN
Classifier: License :: OSI Approved :: GNU General Public License (GPL)
Classifier: Programming Language :: Python :: 3.6
Classifier: Programming Language :: Python :: 3.7
Classifier: Programming Language :: Python :: 3.8
Classifier: Programming Language :: Python :: 3.9
Requires-Python: >=3.6
